{
  "replace": false,
  "values": [
    {
      "id": "minecraft:rotten_flesh",
      "required": false
    },
    {
      "id": "minecraft:cod",
      "required": false
    },
    {
      "id": "minecraft:tropical_fish",
      "required": false
    },
    {
      "id": "minecraft:pufferfish",
      "required": false
    },
    {
      "id": "minecraft:salmon",
      "required": false
    },
    {
      "id": "minecraft:beef",
      "required": false
    },
    {
      "id": "minecraft:porkchop",
      "required": false
    },
    {
      "id": "minecraft:mutton",
      "required": false
    },
    {
      "id": "minecraft:chicken",
      "required": false
    },
    {
      "id": "minecraft:rabbit",
      "required": false
    },
    {
      "id": "minecraft:cooked_chicken",
      "required": false
    },
    {
      "id": "minecraft:cooked_rabbit",
      "required": false
    },
    {
      "id": "minecraft:rabbit_stew",
      "required": false
    },
    {
      "id": "minecraft:cooked_porkchop",
      "required": false
    },
    {
      "id": "minecraft:cooked_cod",
      "required": false
    },
    {
      "id": "minecraft:cooked_beef",
      "required": false
    },
    {
      "id": "minecraft:cooked_mutton",
      "required": false
    },
    {
      "id": "minecraft:cooked_salmon",
      "required": false
    },
    {
      "id": "minecraft:spider_eye",
      "required": false
    },
    {
      "id": "brewery:pork_knuckle",
      "required": false
    },
    {
      "id": "brewery:sausage",
      "required": false
    },
    {
      "id": "#vinery:grapejuice",
      "required": false
    },
    {
      "id": "#vinery:wine",
      "required": false
    },
    {
      "id": "brewery:beer_wheat",
      "required": false
    },
    {
      "id": "brewery:beer_barley",
      "required": false
    },
    {
      "id": "brewery:beer_hops",
      "required": false
    },
    {
      "id": "brewery:beer_haley",
      "required": false
    },
    {
      "id": "brewery:whiskey_jojannik",
      "required": false
    },
    {
      "id": "brewery:whiskey_lilitusinglemalt",
      "required": false
    },
    {
      "id": "brewery:whiskey_cristelwalker",
      "required": false
    },
    {
      "id": "brewery:whiskey_maggoallan",
      "required": false
    },
    {
      "id": "brewery:whiskey_carrasconlabel",
      "required": false
    },
    {
      "id": "candlelight:bolognese",
      "required": false
    },
    {
      "id": "candlelight:chicken_teriyaki",
      "required": false
    },
    {
      "id": "candlelight:beef_tartare",
      "required": false
    },
    {
      "id": "candlelight:fricasse",
      "required": false
    },
    {
      "id": "candlelight:cooked_beef",
      "required": false
    },
    {
      "id": "candlelight:pork_ribs",
      "required": false
    },
    {
      "id": "candlelight:roastbeef_carrots",
      "required": false
    },
    {
      "id": "candlelight:lettuce_beef",
      "required": false
    },
    {
      "id": "candlelight:tropical_fish_supreme",
      "required": false
    },
    {
      "id": "candlelight:salmon_wine",
      "required": false
    },
    {
      "id": "candlelight:chicken_alfredo",
      "required": false
    },
    {
      "id": "candlelight:chicken",
      "required": false
    },
    {
      "id": "candlelight:beef_wellington",
      "required": false
    },
    {
      "id": "meadow:raw_buffalo_meat",
      "required": false
    },
    {
      "id": "meadow:cooked_buffalo_meat",
      "required": false
    },
    {
      "id": "meadow:roasted_ham",
      "required": false
    },
    {
      "id": "meadow:sausage_with_cheese",
      "required": false
    },
    {
      "id": "clutter:raw_venison",
      "required": false
    },
    {
      "id": "clutter:cooked_venison",
      "required": false
    },
    {
      "id": "clutter:raw_venison_ribs",
      "required": false
    },
    {
      "id": "clutter:cooked_venison_ribs",
      "required": false
    },
    {
      "id": "beachparty:raw_mussel_meat",
      "required": false
    },
    {
      "id": "beachparty:cooked_mussel_meat",
      "required": false
    }
  ]
}